LICENSE
MANIFEST.in
README.rst
setup.cfg
setup.py
django_auth_jwt_tenant/__init__.py
django_auth_jwt_tenant/auth.py
django_auth_jwt_tenant/compat.py
django_auth_jwt_tenant/exceptions.py
django_auth_jwt_tenant/mixins.py
django_auth_jwt_tenant/settings.py
django_auth_jwt_tenant/utils.py
django_auth_jwt_tenant.egg-info/PKG-INFO
django_auth_jwt_tenant.egg-info/SOURCES.txt
django_auth_jwt_tenant.egg-info/dependency_links.txt
django_auth_jwt_tenant.egg-info/not-zip-safe
django_auth_jwt_tenant.egg-info/requires.txt
django_auth_jwt_tenant.egg-info/top_level.txt
django_auth_jwt_tenant/tests/__init__.py
django_auth_jwt_tenant/tests/test_models.py
django_auth_jwt_tenant/tests/test_views.py
django_auth_jwt_tenant/tests/urls.py